src/__init__.py
src/raw_acquisition.py
src/ta_acquisition.py
data_acquisition-0.0.1.dist-info/METADATA
data_acquisition-0.0.1.dist-info/WHEEL
data_acquisition-0.0.1.dist-info/top_level.txt
data_acquisition-0.0.1.dist-info/RECORD
