Metadata-Version: 2.1
Name: data-acquisition
Version: 0.0.1
Summary: Stock Data Acquisition
Home-page: UNKNOWN
Author: Scott Hirsch
Author-email: UNKNOWN
License: UNKNOWN
Keywords: python,stock,finance,technical analysis
Platform: UNKNOWN
Classifier: Development Status :: 3 - Alpha
Classifier: Intended Audience :: Education
Classifier: Programming Language :: Python :: 3
Classifier: Operating System :: MacOS :: MacOS X
Classifier: Operating System :: Microsoft :: Windows
Requires-Dist: ta
Requires-Dist: requests
Requires-Dist: pandas
